{
    "Provider": {
        "UB Mannheim": {
            "Bibliographic Info": {
                "DFG-Viewer": "516401319",
                "Title": "Leitende Männer der Wirtschaft und der zugehörigen Verwaltung",
                "Collection(s)": "Hoppenstedt",
                "Language": "Deutsch",
                "Place of Publication": "Berlin",
                "Structure Type": "Darmstadt",
                "OAI-Identifier": "Essen",
                "URN": "Zeitschrift",
                "PURL": "516401319",
                "METS": "urn:nbn:de:bsz:180-dighop-152"
            },
            "List of Volumes": {
                "Overview": [
                    {
                        "Volume": "[03].1951",
                        "Year": "1951",
                        "URL": "https://digi.bib.uni-mannheim.de/hoppenstedt/uebersicht/hs-seitenansicht-uebersicht/?tx_dlf%5Bid%5D=3921&tx_dlf%5Bpage%5D=1&tx_dlf%5Bdouble%5D=0&cHash=3c5a224214fe5baf00844bbe5f5bd484",
                        "METS": "https://digi.bib.uni-mannheim.de/mets/urn:nbn:de:bsz:180-dighop-166"
                    },
                    {
                        "Volume": "[04].1953",
                        "Year": "1953",
                        "URL": "https://digi.bib.uni-mannheim.de/hoppenstedt/uebersicht/hs-seitenansicht-uebersicht/?tx_dlf%5Bid%5D=3919&tx_dlf%5Bpage%5D=1&tx_dlf%5Bdouble%5D=0&cHash=da767044c3cd2183b5f6d09f3f5e2b48",
                        "METS": "https://digi.bib.uni-mannheim.de/mets/urn:nbn:de:bsz:180-dighop-144"
                    }
                ]
            }
        }
    }
}